GRZANKA/__init__.py
GRZANKA-0.22.198.dist-info/METADATA
GRZANKA-0.22.198.dist-info/WHEEL
GRZANKA-0.22.198.dist-info/top_level.txt
GRZANKA-0.22.198.dist-info/RECORD
