Metadata-Version: 2.1
Name: GRZANKA
Version: 0.22.198
Summary: Lobby bot.
Home-page: https://www.youtube.com
Author: Sekkay
License: UNKNOWN
Platform: UNKNOWN
Classifier: Programming Language :: Python :: 3
Classifier: License :: OSI Approved :: MIT License
Classifier: Operating System :: OS Independent
Requires-Dist: crayons
Requires-Dist: fortnitepy
Requires-Dist: BenBotAsync
Requires-Dist: FortniteAPIAsync
Requires-Dist: uvloop
Requires-Dist: sanic (==21.6.2)
Requires-Dist: colorama
Requires-Dist: aiohttp
